sigma/backends/splunk/__init__.py
sigma/backends/splunk/splunk.py
sigma/pipelines/splunk/__init__.py
sigma/pipelines/splunk/splunk.py
pysigma_backend_splunk-1.1.3.dist-info/LICENSE
pysigma_backend_splunk-1.1.3.dist-info/METADATA
pysigma_backend_splunk-1.1.3.dist-info/WHEEL
pysigma_backend_splunk-1.1.3.dist-info/RECORD
