Metadata-Version: 2.1
Name: pysigma-backend-splunk
Version: 1.1.3
Summary: pySigma Splunk backend
Home-page: https://github.com/SigmaHQ/pySigma-backend-splunk
License: LGPL-2.1-only
Author: Thomas Patzke
Author-email: thomas@patzke.org
Requires-Python: >=3.9,<4.0
Classifier: License :: OSI Approved
Classifier: Programming Language :: Python :: 3
Classifier: Programming Language :: Python :: 3.9
Classifier: Programming Language :: Python :: 3.10
Classifier: Programming Language :: Python :: 3.11
Classifier: Programming Language :: Python :: 3.12
Classifier: Programming Language :: Python :: 3.13
Requires-Dist: pysigma (>=0.11.18,<0.12.0)
Project-URL: Repository, https://github.com/SigmaHQ/pySigma-backend-splunk
